setup.py
BinPy/__init__.py
BinPy/base.py
BinPy.egg-info/PKG-INFO
BinPy.egg-info/SOURCES.txt
BinPy.egg-info/dependency_links.txt
BinPy.egg-info/entry_points.txt
BinPy.egg-info/top_level.txt
BinPy/Algorithms/AnalogFormulas.py
BinPy/Algorithms/ExpressionConvert.py
BinPy/Algorithms/ImplementBooleanFunction.py
BinPy/Algorithms/MooreOptimizer.py
BinPy/Algorithms/QuineMcCluskey.py
BinPy/Algorithms/__init__.py
BinPy/Combinational/__init__.py
BinPy/Combinational/combinational.py
BinPy/Gates/__init__.py
BinPy/Gates/connector.py
BinPy/Gates/gates.py
BinPy/Operations/__init__.py
BinPy/Operations/operations.py
BinPy/Sequential/__init__.py
BinPy/Sequential/counters.py
BinPy/Sequential/sequential.py
BinPy/Shell/Shell.py
BinPy/Shell/__init__.py
BinPy/dev/__init__.py
BinPy/dev/parseEquation.py
BinPy/ic/__init__.py
BinPy/ic/base.py
BinPy/ic/series_4000.py
BinPy/ic/series_7400.py
BinPy/ic/series_7400_1.py
BinPy/tests/__init__.py
BinPy/tests/combinational_tests.py
BinPy/tests/gates_tests.py
BinPy/tests/ics_tests.py
BinPy/tests/operations_tests.py
BinPy/tests/sequential_tests.py
BinPy/tests/series_4000_test.py
BinPy/tests/source_tests.py
BinPy/tools/__init__.py
BinPy/tools/digital.py
BinPy/tools/ground.py
BinPy/tools/powersource.py