Metadata-Version: 1.0
Name: BinPy
Version: 0.3
Summary: Virtualizing Electronics
Home-page: http://pypi.python.org/pypi/BinPy/
Author: BinPy Developers
Author-email: binpylib@gmail.com
License: UNKNOWN
Platform: UNKNOWN
